{"一次": 0, "考试": 1, "，": 2, "我": 3, "在": 4, "静静的": 5, "教室": 6, "里": 7, "监考": 8, "巡视": 9, "。": 10, "学生": 11, "都": 12, "低着头": 13, "试卷": 14, "上": 15, "奋笔疾书": 16, "当": 17, "走": 18, "到": 19, "一个": 20, "身旁": 21, "时": 22, "看到": 23, "他": 24, "脚下": 25, "躺": 26, "着": 27, "一支": 28, "笔": 29, "没有": 30, "出": 31, "声": 32, "弯": 33, "下腰": 34, "帮": 35, "把": 36, "捡起来": 37, "轻轻": 38, "放在": 39, "桌上": 40, "像": 41, "什么": 42, "也": 43, "发生": 44, "过": 45, "一样": 46, "过去": 47, "又": 48, "接着": 49, "其他": 50, "地方": 51, "第二次": 52, "走过": 53, "这个": 54, "让": 55, "想到": 56, "的": 57, "是": 58, "故意": 59, "用": 60, "胳膊肘": 61, "碰": 62, "了": 63, "一下": 64, "那": 65, "支笔": 66, "“": 67, "啪": 68, "”": 69, "不偏不倚": 70, "笔落": 71, "脚边": 72, "停下": 73, "脚步": 74, "看着": 75, "很": 76, "坦然": 77, "像是": 78, "无意识": 79, "似的": 80, "斜": 81, "身子": 82, "背对着": 83, "坐在": 84, "凳子": 85, "原来": 86, "平": 87, "胳膊": 88, "立": 89, "起来": 90, "撑": 91, "脑袋": 92, "眼睛": 93, "瞄着": 94, "一只": 95, "手": 96, "胡乱": 97, "地写": 98, "有": 99, "很多": 100, "空白": 101, "已经": 102, "一些": 103, "躁动": 104, "从": 105, "不同": 106, "角落": 107, "不时": 108, "传来": 109, "悉悉": 110, "索索": 111, "声音": 112, "出现": 113, "同学": 114, "身边": 115, "这次": 116, "特意": 117, "经过": 118, "想": 119, "知道": 120, "他会": 121, "不会": 122, "再次": 123, "做出": 124, "那样": 125, "举动": 126, "如出一辙": 127, "！": 128, "掉": 129, "挑衅": 130, "脑子里": 131, "立刻": 132, "跳出": 133, "词语": 134, "意识": 135, "纷纷": 136, "目光": 137, "齐刷刷": 138, "地": 139, "注视": 140, "空气": 141, "顿时": 142, "积聚": 143, "巨大": 144, "能量": 145, "马上": 146, "就要": 147, "爆炸": 148, "怒火": 149, "燃到": 150, "头顶": 151, "不由自主": 152, "扬起": 153, "刚": 154, "开学": 155, "没": 156, "几天": 157, "班里": 158, "小组长": 159, "向": 160, "汇报": 161, "他们": 162, "组就": 163, "刘": 164, "某某": 165, "交": 166, "作业": 167, "随口": 168, "问": 169, "一句": 170, "：": 171, "你": 172, "作业本": 173, "呢": 174, "？": 175, "时候": 176, "能交": 177, "只见": 178, "看": 179, "一眼": 180, "然后": 181, "默默地": 182, "书包": 183, "收拾": 184, "起身": 185, "背": 186, "起": 187, "昂首": 188, "走出": 189, "一": 190, "愣": 191, "阻拦": 192, "因为": 193, "只要": 194, "会": 195, "加大": 196, "逆反心理": 197, "做声": 198, "任由": 199, "出入": 200, "无人之境": 201, "随后": 202, "跟着": 203, "悄悄地": 204, "（": 205, "发现": 206, "）": 207, "从此以后": 208, "明显": 209, "觉得": 210, "和": 211, "关系": 212, "以前": 213, "亲密": 214, "上课": 215, "积极": 216, "举手": 217, "读": 218, "课文": 219, "语文": 220, "能": 221, "按时": 222, "完成": 223, "并": 224, "改错": 225, "据我所知": 226, "只": 227, "做": 228, "可": 229, "这件": 230, "事后": 231, "课上": 232, "高兴": 233, "就": 234, "听": 235, "不": 236, "玩": 237, "东西": 238, "写": 239, "对": 240, "说": 241, "的话": 242, "爱": 243, "搭": 244, "不理": 245, "往往": 246, "沉默": 247, "回答": 248, "找": 249, "谈过": 250, "几次": 251, "就是": 252, "话": 253, "如同": 254, "一天": 255, "中午": 256, "吃过饭": 257, "后": 258, "孙": 259, "给": 260, "田": 261, "糖": 262, "这些": 263, "再": 264, "分": 265, "一部分": 266, "好": 267, "朋友": 268, "拿": 269, "自己": 270, "数": 271, "没想到": 272, "冲过去": 273, "顺手": 274, "抓起": 275, "一把": 276, "还": 277, "二话不说": 278, "双手": 279, "死死地": 280, "掐住": 281, "脖子": 282, "当时": 283, "高": 284, "老师": 285, "看见": 286, "立马": 287, "阻止": 288, "撒手": 289, "眼看": 290, "舌头": 291, "吐出来": 292, "们": 293, "一起": 294, "动手": 295, "试图": 296, "手中": 297, "解脱": 298, "下来": 299, "无济于事": 300, "见状": 301, "灵机一动": 302, "衣服": 303, "身上": 304, "退下来": 305, "赶紧": 306, "隔离": 307, "叫田": 308, "去": 309, "办公室": 310, "休息": 311, "第一周": 312, "领教": 313, "这娃": 314, "霸气": 315, "威武": 316, "课间": 317, "我进": 318, "女孩": 319, "哭哭啼啼": 320, "郭郭": 321, "要": 322, "弄死": 323, "…": 324, "听到": 325, "此": 326, "心": 327, "紧紧": 328, "抽": 329, "追问": 330, "才": 331, "明白": 332, "不想": 333, "她": 334, "怂恿": 335, "旁边": 336, "另": 337, "男生": 338, "拿出": 339, "小": 340, "剪刀": 341, "来": 342, "恶狠狠": 343, "威胁": 344, "道": 345, "过来": 346, "烦": 347, "我们": 348, "郭": 349, "出来": 350, "了解": 351, "情况": 352, "那里": 353, "安静": 354, "不过": 355, "三秒": 356, "不停": 357, "转着": 358, "身": 359, "抖": 360, "腿": 361, "迷人": 362, "大": 363, "充满": 364, "不屑": 365, "坚持": 366, "认为": 367, "先招": 368, "秉承": 369, "人若犯": 370, "我必": 371, "奉还": 372, "原则": 373, "一口咬定": 374, "罪有应得": 375, "而": 376, "之语": 377, "无": 378, "任何": 379, "不妥": 380, "劝慰": 381, "开导": 382, "全然": 383, "时不时": 384, "几句": 385, "浑话": 386, "内心": 387, "早已": 388, "被": 389, "得": 390, "够呛": 391, "但": 392, "心里": 393, "这样": 394, "态度": 395, "一方面": 396, "个性": 397, "使然": 398, "更": 399, "重要": 400, "认可": 401, "半路": 402, "接班": 403, "年轻": 404, "一副": 405, "天下": 406, "唯我独尊": 407, "、": 408, "凌人": 409, "气势": 410, "最后": 411, "僵持不下": 412, "妈妈": 413, "打": 414, "电话": 415, "威严": 416, "下意识": 417, "错误": 418, "勉强": 419, "歉": 420, "入学": 421, "小浩": 422, "更是": 423, "状态": 424, "百出": 425, "上课时": 426, "动动": 427, "这儿": 428, "看看": 429, "那儿": 430, "书本": 431, "文具": 432, "弄": 433, "七零八落": 434, "；": 435, "常常": 436, "发出": 437, "怪声": 438, "或": 439, "擅自": 440, "离开": 441, "座位": 442, "或者": 443, "咬": 444, "铅笔": 445, "吮": 446, "手指": 447, "切": 448, "橡皮": 449, "活跃": 450, "异常": 451, "跟": 452, "追逐": 453, "打闹": 454, "甚至": 455, "打伤": 456, "可怕": 457, "批评": 458, "他时": 459, "情绪": 460, "变得": 461, "非常": 462, "极端": 463, "大声": 464, "喊叫": 465, "顶撞": 466, "跺脚": 467, "推": 468, "桌子": 469, "耳光": 470, "文具盒": 471, "撞": 472, "额头": 473, "小胡": 474, "个子": 475, "较": 476, "长得": 477, "比": 478, "同龄": 479, "孩子": 480, "靠墙边": 481, "倒数": 482, "第二个": 483, "位置": 484, "总是": 485, "懒散": 486, "样子": 487, "打扰": 488, "其他同学": 489, "紧张": 490, "打架": 491, "欺负": 492, "弱小": 493, "但是": 494, "组织": 495, "活动": 496, "特别": 497, "平时": 498, "表现": 499, "不好": 500, "机会": 501, "上场": 502, "不让": 503, "变本加厉": 504, "扰乱": 505, "课堂": 506, "形成": 507, "一种": 508, "恶性循环": 509, "美术课": 510, "歪歪扭扭": 511, "坐": 512, "手拿着": 513, "懒洋洋": 514, "趴在": 515, "别的": 516, "画画": 517, "不画": 518, "而是": 519, "一有": 520, "人家": 521, "一到": 522, "提问": 523, "恨不得": 524, "把手": 525, "举到": 526, "讲台": 527, "上去": 528, "有时": 529, "叫": 530, "答": 531, "上来": 532, "坐下": 533, "之后": 534, "还是": 535, "新学期": 536, "刚刚": 537, "两周": 538, "李鹏": 539, "宇": 540, "已": 541, "状况": 542, "第一天": 543, "校园": 544, "门口": 545, "公开": 546, "摆擂台": 547, "原因": 548, "简单": 549, "上学": 550, "正在": 551, "执勤": 552, "安保": 553, "结果": 554, "小鹏宇": 555, "飞腿": 556, "连续": 557, "命中": 558, "不幸": 559, "中招": 560, "真是": 561, "这位": 562, "哭笑不得": 563, "忙": 564, "赔不是": 565, "小浩是": 566, "全校师生": 567, "贴": 568, "调皮": 569, "王": 570, "捣蛋鬼": 571, "标签": 572, "真": 573, "分班": 574, "难缠": 575, "魔头": 576, "分到": 577, "班": 578, "果然": 579, "不久": 580, "就让": 581, "见识": 582, "厉害": 583, "—": 584, "总": 585, "有所作为": 586, "冒": 587, "一腔": 588, "引得": 589, "全班": 590, "哄堂大笑": 591, "镜子": 592, "反射": 593, "太阳光": 594, "晃": 595, "组长": 596, "收发": 597, "伸出": 598, "一条": 599, "绊倒": 600, "伎俩": 601, "层出不穷": 602, "偷偷": 603, "往": 604, "女生": 605, "背后": 606, "贴画": 607, "猪头": 608, "纸条": 609, "趁": 610, "其": 611, "不备": 612, "搬开": 613, "坐空": 614, "摔个": 615, "四脚朝天": 616, "捉来": 617, "毛毛虫": 618, "塞进": 619, "吓": 620, "哇哇": 621, "大叫": 622, "经常": 623, "满纸": 624, "红叉叉": 625, "迟交": 626, "根本": 627, "测试": 628, "20": 629, "多分": 630, "家常便饭": 631, "小涵": 632, "大嗓门": 633, "班级": 634, "纪律": 635, "每天": 636, "值周": 637, "扣分": 638, "每": 639, "忍不住": 640, "严厉": 641, "警告": 642, "不留情面": 643, "次数": 644, "多": 645, "敌意": 646, "越来越": 647, "丝毫": 648, "没改": 649, "罢了": 650, "放": 651, "蜗牛": 652, "虫子": 653, "之类": 654, "办公桌": 655, "人": 656, "上乱": 657, "丢": 658, "纸团": 659, "朝": 660, "吐": 661, "唾沫": 662, "课": 663, "上面": 664, "做鬼脸": 665, "用干": 666, "纸巾": 667, "沾": 668, "水": 669, "天花板": 670, "超": 671, "粉笔": 672, "头": 673, "课外书": 674, "算好": 675, "课下": 676, "朝着": 677, "泼水": 678, "乱丢纸屑": 679, "水瓶": 680, "满": 681, "楼道": 682, "洒水": 683, "不回": 684, "躲": 685, "厕所": 686, "藏": 687, "图书馆": 688, "等": 689, "乱串": 690, "随便": 691, "拿走": 692, "别人": 693, "随意": 694, "踢打": 695, "低年级": 696, "情节": 697, "最": 698, "严重": 699, "曾": 700, "试图用": 701, "开水": 702, "泼洒": 703, "本班": 704, "噩梦": 705, "敲门": 706, "某": 707, "天": 708, "吃": 709, "午饭": 710, "三年级": 711, "小女孩": 712, "跑": 713, "泪水": 714, "涟涟": 715, "地向": 716, "告状": 717, "阿毛": 718, "今天上午": 719, "两次": 720, "现在": 721, "肚子": 722, "疼": 723, "今天": 724, "一点": 725, "招惹": 726, "见": 727, "委屈": 728, "先是": 729, "安抚": 730, "承诺": 731, "一定": 732, "狠狠": 733, "回": 734, "班上": 735, "稍后": 736, "上午": 737, "自习": 738, "承认": 739, "确实": 740, "那个": 741, "女同学": 742, "并且": 743, "理由": 744, "依然": 745, "大发雷霆": 746, "选择": 747, "将心比心": 748, "经历": 749, "劝解": 750, "保证": 751, "下次": 752, "不再": 753, "十分": 754, "同意": 755, "爸爸": 756, "学校": 757, "总夸": 758, "懂事": 759, "关爱": 760, "学前班": 761, "学期": 762, "小勇": 763, "没写": 764, "完想": 765, "喝水": 766, "完": 767, "生气": 768, "不写": 769, "顶嘴": 770, "不服气": 771, "一气之下": 772, "家": 773, "回来": 774, "脏话": 775, "打人": 776, "啦": 777, "只是": 778, "平淡": 779, "嗯": 780, "一声": 781, "性格": 782, "偏激": 783, "每次": 784, "小事": 785, "与": 786, "大吵大闹": 787, "自控": 788, "能力": 789, "很差": 790, "下": 791, "调皮捣蛋": 792, "不是": 793, "动": 794, "扭过去": 795, "嘴巴": 796, "说个": 797, "下课": 798, "骂人": 799, "心目": 800, "中": 801, "问题": 802, "不满": 803, "大家": 804, "喜欢": 805, "所以": 806, "本该": 807, "欢笑": 808, "年龄": 809, "却": 810, "自卑": 811, "愤怒": 812, "失望": 813, "占据": 814, "小小的": 815, "心窗": 816, "关上": 817, "集体": 818, "属于": 819, "格格不入": 820, "笑脸": 821, "只有": 822, "脸": 823, "冷冰冰": 824, "这": 825, "朵花": 826, "花": 827, "开放": 828, "吗": 829, "卷子": 830, "抹平": 831, "耳边": 832, "为": 833, "你好": 834, "怕": 835, "卷儿": 836, "快": 837, "吧": 838, "我本": 839, "以为": 840, "乖乖": 841, "听话": 842, "可是": 843, "一张": 844, "纸": 845, "画": 846, "小人儿": 847, "一看": 848, "班主任": 849, "钢笔尖": 850, "地乱": 851, "扎": 852, "一气": 853, "写道": 854, "哈哈": 855, "赢": 856, "笑": 857, "谁": 858, "理解": 859, "为什么": 860, "该": 861, "伤心": 862, "啊": 863, "收": 864, "反对": 865, "为了": 866, "淡化": 867, "对抗": 868, "后面": 869, "关注": 870, "继续": 871, "地扎": 872, "嘴里": 873, "嘟囔": 874, "小敬": 875, "小便": 876, "恶作剧": 877, "心理": 878, "作祟": 879, "竟": 880, "尿": 881, "洒": 882, "隔壁": 883, "简直": 884, "太": 885, "匪夷所思": 886, "刷新": 887, "从教": 888, "十来": 889, "年": 890, "认知": 891, "望": 892, "一脸": 893, "故作": 894, "无知": 895, "状": 896, "熊熊燃烧": 897, "话语": 898, "劈头盖脸": 899, "地直": 900, "砸": 901, "然而": 902, "狂风暴雨": 903, "般的": 904, "训斥": 905, "除了": 906, "脸上": 907, "显现出": 908, "些许": 909, "无所谓": 910, "外": 911, "似乎": 912, "别": 913, "无益": 914, "处": 915, "毕竟": 916, "还要": 917, "烂摊子": 918, "受害者": 919, "细细": 920, "询问": 921, "以求": 922, "将": 923, "恶劣影响": 924, "降到": 925, "最低": 926, "疲于": 927, "应付": 928, "由小敬": 929, "引起": 930, "种种": 931, "恶果": 932, "而小敬": 933, "越发": 934, "沉默寡言": 935, "动不动": 936, "拳头": 937, "解决问题": 938, "无奈": 939, "苦思": 940, "不得": 941, "良策": 942, "多动": 943, "几分": 944, "学习": 945, "兴趣": 946, "要么": 947, "搞小动作": 948, "自言自语": 949, "影响": 950, "动手动脚": 951, "即使": 952, "完整": 953, "书写": 954, "相当": 955, "潦草": 956, "·": 957, "插入": 958, "以来": 959, "行为习惯": 960, "讲话": 961, "嬉笑": 962, "出怪": 963, "宿舍": 964, "肆无忌惮": 965, "四楼": 966, "矿泉水瓶": 967, "向下": 968, "带": 969, "鞭炮": 970, "偷放": 971, "似": 972, "一匹": 973, "脱缰": 974, "野马": 975, "服从": 976, "管理": 977, "多次": 978, "家长": 979, "沟通": 980, "用尽": 981, "各种": 982, "教育": 983, "方法": 984, "收效甚微": 985, "本学期": 986, "3": 987, "月份": 988, "伊始": 989, "一周": 990, "时间": 991, "内": 992, "次大": 993, "事件": 994, "受到": 995, "劝": 996, "转学": 997, "处分": 998, "恳切": 999, "要求": 1000, "试读": 1001, "下午": 1002, "我刚": 1003, "走进": 1004, "哭声": 1005, "烨": 1006, "同桌": 1007, "哭": 1008, "扔": 1009, "地上": 1010, "书": 1011, "撒落": 1012, "一地": 1013, "七嘴八舌": 1014, "说烨": 1015, "一年级": 1016, "搞": 1017, "心乱如麻": 1018, "制止": 1019, "轻声": 1020, "为何": 1021, "轻描淡写": 1022, "好玩": 1023, "第二": 1024, "早": 1025, "一片狼藉": 1026, "大部分": 1027, "散落": 1028, "外面": 1029, "本子": 1030, "浸": 1031, "许多": 1032, "墨水": 1033, "不用说": 1034, "一致": 1035, "指向": 1036, "则": 1037, "若无其事": 1038, "云淡风轻": 1039, "地说": 1040, "某日": 1041, "一脚": 1042, "踏进": 1043, "门": 1044, "哭诉": 1045, "小琦打": 1046, "于是": 1047, "疯跑": 1048, "小琦叫": 1049, "怎么": 1050, "玩玩": 1051, "而已": 1052, "叫作": 1053, "更加": 1054, "语气": 1055, "好景不长": 1056, "第二天": 1057, "思品": 1058, "急匆匆": 1059, "两个": 1060, "拉": 1061, "不开": 1062, "两人": 1063, "连思品": 1064, "匆匆": 1065, "赶来": 1066, "小宇": 1067, "小伟": 1068, "两人正": 1069, "打得": 1070, "不可开交": 1071, "一边": 1072, "不敢": 1073, "上前": 1074, "走上": 1075, "前问": 1076, "同时": 1077, "先": 1078, "连": 1079, "事情": 1080, "起因": 1081, "路上": 1082, "有意识": 1083, "观察": 1084, "行为": 1085, "举止": 1086, "还好": 1087, "顾": 1088, "走路": 1089, "小宇边": 1090, "走边": 1091, "打小伟": 1092, "一会": 1093, "揪": 1094, "停下来": 1095, "一路": 1096, "大致": 1097, "谁是谁非": 1098, "不动声色": 1099, "分别": 1100, "讲": 1101, "互相": 1102, "不能": 1103, "听见": 1104, "对方": 1105, "断断续续": 1106, "讲述": 1107, "分辨": 1108, "刚才": 1109, "基本一致": 1110, "先动": 1111, "犯错": 1112, "谁知": 1113, "出口": 1114, "开始": 1115, "号啕大哭": 1116, "好像": 1117, "受": 1118, "天大": 1119, "边": 1120, "完全": 1121, "无视": 1122, "存在": 1123, "停止": 1124, "抡": 1125, "小拳头": 1126, "打来": 1127, "准备": 1128, "大闹": 1129, "不断": 1130, "地有": 1131, "告小宇": 1132, "吵架": 1133, "全班同学": 1134, "数学课": 1135, "大声嚷嚷": 1136, "无法": 1137, "撞倒": 1138, "往人": 1139, "黑板擦": 1140, "还有": 1141, "数学老师": 1142, "总之": 1143, "坏事": 1144, "好事": 1145, "一件": 1146, "看书": 1147, "体育老师": 1148, "找到": 1149, "看得出来": 1150, "激动": 1151, "哪个": 1152, "调皮鬼": 1153, "惹": 1154, "放下": 1155, "书笑": 1156, "你们": 1157, "小轩": 1158, "最近": 1159, "捣乱": 1160, "可好": 1161, "学会": 1162, "顶牛": 1163, "气呼呼": 1164, "班中": 1165, "一位": 1166, "倾向": 1167, "小繁": 1168, ",": 1169, "总会": 1170, "突然": 1171, "奇怪": 1172, "响声": 1173, "某位": 1174, "偷": 1175, "喝": 1176, "一口": 1177, "忽然": 1178, "低头": 1179, "不知": 1180, "课桌": 1181, "下面": 1182, "钻出来": 1183, "蹲": 1184, "对于": 1185, "伤透": 1186, "脑筋": 1187, "出点": 1188, "意外": 1189, "事": 1190, "难以": 1191, "应对": 1192, "引用": 1193, "关于": 1194, "动物": 1195, "视频": 1196, "猴子": 1197, "夸张": 1198, "嗷嗷": 1199, "怪叫": 1200, "配着": 1201, "鬼脸": 1202, "哄然大笑": 1203, "吸引": 1204, "一两个": 1205, "男孩子": 1206, "紧接着": 1207, "模仿": 1208, "动作": 1209, "叫声": 1210, "导致": 1211, "搞怪": 1212, "集中精力": 1213, "于": 1214, "第一次": 1215, "可爱": 1216, "实则": 1217, "动怒": 1218, "发": 1219, "脾气": 1220, "虽然": 1221, "当堂": 1222, "收敛": 1223, "这种": 1224, "来管": 1225, "生效": 1226, "多久": 1227, "难道": 1228, "隔": 1229, "几日": 1230, "发脾气": 1231, "维持": 1232, "秩序": 1233, "通过": 1234, "得知": 1235, "从小": 1236, "有些": 1237, "比较": 1238, "好动": 1239, "好斗": 1240, "冒犯": 1241, "常": 1242, "同一个": 1243, "小区": 1244, "幼儿园": 1245, "出了名": 1246, "惹事": 1247, "一蹴而就": 1248, "多方": 1249, "渠道": 1250, "如今": 1251, "责任": 1252, "并未": 1253, "本身": 1254, "所": 1255, "造成": 1256, "小时候": 1257, "由": 1258, "爷爷": 1259, "奶奶": 1260, "看管": 1261, "那种": 1262, "娇惯": 1263, "溺爱": 1264, "自我": 1265, "中心": 1266, "特点": 1267, "武力": 1268, "解决": 1269, "一切": 1270, "方式": 1271, "浩浩": 1272, "成为": 1273, "一年": 1274, "三班": 1275, "麻烦": 1276, "接踵而来": 1277, "第": 1278, "一堂课": 1279, "所有": 1280, "正": 1281, "聚精会神": 1282, "听讲": 1283, "无故": 1284, "大哭": 1285, "一番": 1286, "听不进去": 1287, "听不懂": 1288, "稍稍": 1289, "平息": 1290, "回到": 1291, "伸手": 1292, "莫名其妙": 1293, "接下来": 1294, "一团糟": 1295, "四处": 1296, "溜达": 1297, "打滚": 1298, "吃饭": 1299, "尖叫": 1300, "饭": 1301, "下课时": 1302, "脱": 1303, "裤子": 1304, "派": 1305, "站队": 1306, "闹": 1307, "音乐": 1308, "不学": 1309, "唱": 1310, "美术": 1311, "撕": 1312, "第三年": 1313, "特殊": 1314, "复读生": 1315, "前": 1316, "告诉": 1317, "个": 1318, "学习成绩": 1319, "差": 1320, "攻击性": 1321, "很强": 1322, "惹是生非": 1323, "头疼": 1324, "嫌弃": 1325, "想着": 1326, "镇住": 1327, "一般": 1328, "否则": 1329, "以后": 1330, "难": 1331, "名不虚传": 1332, "情绪低落": 1333, "毫无": 1334, "胡": 1335, "打乱": 1336, "一言不合": 1337, "就挥起": 1338, "短短几天": 1339, "屡屡": 1340, "科任": 1341, "谈话": 1342, "真让人": 1343, "带领": 1344, "操场上": 1345, "铲雪": 1346, "班干部": 1347, "带到": 1348, "面前": 1349, "把头": 1350, "埋到": 1351, "胸前": 1352, "任": 1353, "处置": 1354, "究竟": 1355, "表情": 1356, "抬起": 1357, "下巴": 1358, "一双": 1359, "戒备": 1360, "抿": 1361, "两只": 1362, "紧握": 1363, "这是": 1364, "仇恨": 1365, "姿态": 1366, "随时": 1367, "还击": 1368, "读完": 1369, "短信": 1370, "嵩": 1371, "影子": 1372, "眼前": 1373, "清晰": 1374, "贵州": 1375, "男孩儿": 1376, "虎头虎脑": 1377, "活泼": 1378, "机灵": 1379, "特有": 1380, "男子汉": 1381, "气概": 1382, "有事没事": 1383, "总爱去": 1384, "逗弄": 1385, "做作业时": 1386, "爱耍": 1387, "小聪明": 1388, "偷工减料": 1389, "常事": 1390, "不绝于耳": 1391, "小辫儿": 1392, "体育课": 1393, "吓唬": 1394, "不管": 1395, "和颜悦色": 1396, "循循善诱": 1397, "暴风骤雨": 1398, "式": 1399, "依旧": 1400, "稳如泰山": 1401, "我行我素": 1402, "父母": 1403, "效果": 1404, "记得": 1405, "闷热": 1406, "闯祸": 1407, "漫画书": 1408, "公然": 1409, "颜面": 1410, "无存": 1411, "扫地": 1412, "进": 1413, "不假思索": 1414, "请来": 1415, "辛": 1416, "男": 1417, "8": 1418, "岁": 1419, "级新生": 1420, "接": 1421, "插嘴": 1422, "从不": 1423, "破坏": 1424, "课堂纪律": 1425, "东张西望": 1426, "就算": 1427, "拉着": 1428, "前后左右": 1429, "说话": 1430, "邻居": 1431, "小朋友": 1432, "个别": 1433, "那去": 1434, "个样": 1435, "歪": 1436, "开溜": 1437, "不念": 1438, "换个": 1439, "小楚": 1440, "太烦人": 1441, "老": 1442, "乱": 1443, "讲卫生": 1444, "随地吐痰": 1445, "急躁": 1446, "矛盾": 1447, "管不住": 1448, "手和口": 1449, "不到": 1450, "几句话": 1451, "惹不起": 1452, "愿意": 1453, "交朋友": 1454, "任课老师": 1455, "反映": 1456, "老爱": 1457, "接下": 1458, "嘴": 1459, "守纪律": 1460, "李老师": 1461, "小羽": 1462, "小子": 1463, "居然": 1464, "找事": 1465, "决定": 1466, "利用": 1467, "好好": 1468, "严肃": 1469, "随即": 1470, "低下": 1471, "转向": 1472, "满脸": 1473, "抽噎": 1474, "双子座": 1475, "相配": 1476, "琪琪": 1477, "结婚": 1478, "侮辱": 1479, "人格": 1480, "反过来说": 1481, "错": 1482, "不该": 1483, "吵": 1484, "实在": 1485, "忍无可忍": 1486, "其实": 1487, "几架": 1488, "过时": 1489, "碰撞": 1490, "他人": 1491, "堵着": 1492, "进出": 1493, "喷": 1494, "一身": 1495, "等等": 1496, "说一不二": 1497, "拳脚相加": 1498, "轩哥": 1499, "不论": 1500, "怎样": 1501, "改变": 1502, "照样": 1503, "里面": 1504, "吵吵嚷嚷": 1505, "站": 1506, "椅子": 1507, "瞪": 1508, "耀武扬威": 1509, "厉声": 1510, "干什么": 1511, "不买账": 1512, "不但": 1513, "反而": 1514, "踏上": 1515, "害怕": 1516, "乜斜": 1517, "挑战": 1518, "教书": 1519, "这么": 1520, "多年": 1521, "遇到": 1522, "不少": 1523, "碰到": 1524, "不怕": 1525, "不懂事": 1526, "故事": 1527, "重复": 1528, "上演": 1529, "1993": 1530, "年初": 1531, "师范学校": 1532, "毕业": 1533, "来到": 1534, "文化": 1535, "小学": 1536, "有名": 1537, "四大": 1538, "混": 1539, "留守": 1540, "儿童": 1541, "孤儿": 1542, "踢": 1543, "碎": 1544, "明天": 1545, "打哭": 1546, "三天两头": 1547, "常有": 1548, "孤立无助": 1549, "深知": 1550, "缺乏": 1551, "打骂": 1552, "往外": 1553, "少": 1554, "换": 1555, "宣泄": 1556, "手扳": 1557, "住": 1558, "贾老师": 1559, "怒吼": 1560, "靠": 1561, "坐于": 1562, "冲": 1563, "主任": 1564, "不关": 1565, "历历在目": 1566, "之间": 1567, "冲突": 1568, "变": 1569, "战场": 1570, "故": 1571, "又称": 1572, "石": 1573, "吼吼": 1574, "偷藏": 1575, "手机": 1576, "根据": 1577, "线索": 1578, "分析": 1579, "目标": 1580, "明确": 1581, "悄悄": 1582, "坚定": 1583, "相信": 1584, "真的": 1585, "一瞬间": 1586, "动摇": 1587, "希望": 1588, "两扇": 1589, "心灵": 1590, "之窗": 1591, "端倪": 1592, "对视": 1593, "几分钟": 1594, "花池": 1595, "!": 1596, "不知情": 1597, "不可否认": 1598, "需要": 1599, "心思": 1600, "指正": 1601, "引导": 1602, "群体": 1603, "突出": 1604, "初": 1605, "见面": 1606, "阶段": 1607, "固有": 1608, "星期": 1609, "接触": 1610, "鲜明": 1611, "已然": 1612, "呈现": 1613, "聪明": 1614, "思考": 1615, "想法": 1616, "发言": 1617, "好评": 1618, "与此同时": 1619, "个人": 1620, "逐渐": 1621, "显现": 1622, "六岁": 1623, "争强好胜": 1624, "拳脚": 1625, "和平": 1626, "玩乐": 1627, "看来": 1628, "拍": 1629, "玩耍": 1630, "恶意": 1631, "小伙伴": 1632, "一次次": 1633, "抱怨": 1634, "接受": 1635, "交流": 1636, "愤然": 1637, "没错": 1638, "道歉": 1639, "不要": 1640, "谅解": 1641, "所有人": 1642, "误会": 1643, "二年级": 1644, "长大": 1645, "淘气": 1646, "脏兮兮": 1647, "评批": 1648, "满嘴": 1649, "盯": 1650, "气鼓鼓": 1651, "地掉": 1652, "眼泪": 1653, "放学": 1654, "队里": 1655, "罚": 1656, "出队": 1657, "一小": 1658, "会儿": 1659, "呗": 1660, "这里": 1661, "回家": 1662, "气": 1663, "火冒三丈": 1664, "男生女生": 1665, "说服教育": 1666, "一两天": 1667, "过后": 1668, "路过": 1669, "小文": 1670, "大打出手": 1671, "鸡毛蒜皮": 1672, "小事儿": 1673, "光": 1674, "伤脑筋": 1675, "自从": 1676, "我接": 1677, "几乎": 1678, "一桌": 1679, "敬而远之": 1680, "办法": 1681, "只好": 1682, "雅座": 1683, "伺候": 1684, "软硬兼施": 1685, "成效": 1686, "不仅": 1687, "相反": 1688, "敌视": 1689, "一直": 1690, "哪": 1691, "正当": 1692, "冥思苦想": 1693, "无计可施": 1694, "一场": 1695, "篮球赛": 1696, "使": 1697, "转机": 1698, "正常": 1699, "太多": 1700, "开着": 1701, "窗": 1702, "爬": 1703, "窗台": 1704, "窗口": 1705, "手舞足蹈": 1706, "几楼": 1707, "做法": 1708, "曾经": 1709, "吓坏": 1710, "而且": 1711, "挨打": 1712, "足够": 1713, "见怪不怪": 1714, "人理": 1715, "无论是": 1716, "一人": 1717, "独处": 1718, "闲着": 1719, "念念有词": 1720, "旁若无人": 1721, "投入": 1722, "乐在其中": 1723, "普通": 1724, "一下子": 1725, "回归": 1726, "原点": 1727, "会因": 1728, "一点儿": 1729, "争吵": 1730, "连来": 1731, "开": 1732, "家长会": 1733, "面对": 1734, "焦头烂额": 1735, "这天": 1736, "小萍": 1737, "请假": 1738, "有事": 1739, "关切": 1740, "地问": 1741, "支吾": 1742, "不肯": 1743, "那好": 1744, "请": 1745, "情愿": 1746, "父亲": 1747, "打电话": 1748, "人接": 1749, "显得": 1750, "着急": 1751, "烦躁": 1752, "一会儿": 1753, "拨": 1754, "一回": 1755, "接通": 1756, "一旁": 1757, "抹": 1758, "生病": 1759, "住院": 1760, "有人": 1761, "照顾": 1762, "而小萍": 1763, "上班": 1764, "回不去": 1765, "一岁": 1766, "半": 1767, "弟弟": 1768, "家里": 1769, "病中": 1770, "因此": 1771, "半天": 1772, "假": 1773, "回去": 1774, "照看": 1775, "很小": 1776, "可以": 1777, "不作声": 1778, "只顾": 1779, "不用": 1780, "管": 1781, "讨厌": 1782, "极力": 1783, "吼起来": 1784, "我边": 1785, "应声": 1786, "茶杯": 1787, "迎上去": 1788, "强装": 1789, "镇定": 1790, "仓促": 1791, "步态": 1792, "焦灼": 1793, "眼神": 1794, "无不": 1795, "传递": 1796, "信息": 1797, "不妙": 1798, "倾下": 1799, "快语": 1800, "小昱": 1801, "小泽打": 1802, "接手": 1803, "小心": 1804, "撞碎": 1805, "玻璃": 1806, "成": 1807, "第一个": 1808, "认识": 1809, "捣蛋": 1810, "一颗": 1811, "定时": 1812, "炸弹": 1813, "神经": 1814, "下课后": 1815, "提笔": 1816, "批作业": 1817, "风风火火": 1818, "跑过来": 1819, "如何": 1820, "减少": 1821, "表扬": 1822, "顺耳": 1823, "屡教不改": 1824, "习惯": 1825, "一味": 1826, "麻木": 1827, "短短的": 1828, "从没": 1829, "直视": 1830, "游离": 1831, "透着": 1832, "叛逆": 1833, "留下": 1834, "第一印象": 1835, "不服": 1836, "照管": 1837, "果不其然": 1838, "出言": 1839, "以": 1840, "捉弄": 1841, "为乐": 1842, "奇异": 1843, "注目": 1844, "干扰": 1845, "课堂秩序": 1846, "从来": 1847, "字": 1848, "形容": 1849, "用小棒": 1850, "戳": 1851, "好看": 1852, "通常": 1853, "当作": 1854, "耳旁风": 1855, "作": 1856, "呆": 1857, "花圃": 1858, "捉": 1859, "乌烟瘴气": 1860, "谈起": 1861, "摇头": 1862, "叹气": 1863, "颇": 1864, "微词": 1865, "聊天": 1866, "旁敲侧击": 1867, "表示": 1868, "教过": 1869, "如数家珍": 1870, "似地": 1871, "倒": 1872, "许许多多": 1873, "丰功伟绩": 1874, ":": 1875, "共同": 1876, "愿望": 1877, "要是": 1878, "睡": 1879, "觉": 1880, "阿弥陀佛": 1881, "峥": 1882, "黄荣": 1883, "剪": 1884, "圆圆的": 1885, "洞": 1886, "手掌心": 1887, "那么": 1888, "记": 1889, "名字": 1890, "气愤": 1891, "之余": 1892, "暴打": 1893, "提起": 1894, "小冬": 1895, "倔": 1896, "全校": 1897, "出名": 1898, "前任": 1899, "追": 1900, "倔强": 1901, "自尊心": 1902, "特强": 1903, "半点": 1904, "这时": 1905, "有个": 1906, "小男生": 1907, "转身": 1908, "正好": 1909, "看在眼里": 1910, "拽": 1911, "膀子": 1912, "扶正": 1913, "一时": 1914, "那边": 1915, "理会": 1916, "趁机": 1917, "打量": 1918, "鞋带": 1919, "松": 1920, "立即": 1921, "提醒": 1922, "系": 1923, "不耐烦": 1924, "怎么样": 1925, "帮助": 1926, "小虎": 1927, "刚入": 1928, "不折不扣": 1929, "睡觉": 1930, "下位": 1931, "乱跑": 1932, "课间操": 1933, "骚扰": 1934, "同伴": 1935, "路队": 1936, "凡是": 1937, "不良习惯": 1938, "蔓延": 1939, "坐不住": 1940, "或是": 1941, "吐口": 1942, "那天": 1943, "单独": 1944, "板书": 1945, "几个": 1946, "小组": 1947, "跳": 1948, "扇": 1949, "两": 1950, "巴掌": 1951, "......": 1952, "气得": 1953, "眼冒金星": 1954, "已到": 1955, "崩溃": 1956, "边缘": 1957, "告诫": 1958, "轻言": 1959, "放弃": 1960, "家庭": 1961, "头发": 1962, "剪得": 1963, "不堪入目": 1964, "一怒之下": 1965, "尺子": 1966, "手心": 1967, "这回": 1968, "没跑": 1969, "老老实实": 1970, "地站": 1971, "忐忑": 1972, "不语": 1973, "稳定": 1974, "不顺心": 1975, "课室": 1976, "大骂": 1977, "众多": 1978, "小妍": 1979, "掐": 1980, "抓伤": 1981, "捶打": 1982, "不止一次": 1983, "地被": 1984, "揭发": 1985, "钱": 1986, "其它": 1987, "零食": 1988, "捂着脸": 1989, "鼻涕": 1990, "擦": 1991, "我望": 1992, "红肿": 1993, "腾地": 1994, "烧": 1995, "三步并作两步": 1996, "拎": 1997, "一半": 1998, "姗姗来迟": 1999, "礼貌": 2000, "推门": 2001, "进来": 2002, "叫住": 2003, "出去": 2004, "重": 2005, "尊重": 2006, "最起码": 2007, "挤眉弄眼": 2008, "根本无法": 2009, "计算器": 2010, "风波": 2011, "之": 2012, "李才": 2013, "王昌扬": 2014, "歉意": 2015, "领情": 2016, "在校": 2017, "当耳边风": 2018, "韦": 2019, "林欢": 2020, "一排": 2021, "刺耳": 2022, "响起": 2023, "打断": 2024, "讲课": 2025, "听课": 2026, "不约而同": 2027, "很快": 2028, "扭向": 2029, "圆珠笔": 2030, "踩": 2031, "硬是": 2032, "赔": 2033, "蛮横": 2034, "无休止": 2035, "地用": 2036, "胳膊肘儿": 2037, "小洋": 2038, "进班起": 2039, "每当": 2040, "理直气壮": 2041, "应该": 2042, "进行": 2043, "改掉": 2044, "不良行为": 2045, "小豪": 2046, "注意力": 2047, "集中": 2048, "较差": 2049, "成绩": 2050, "打打闹闹": 2051, "还会": 2052, "争执": 2053, "间": 2054, "瞥见": 2055, "金鱼": 2056, "光秃秃": 2057, "尾部": 2058, "鱼尾": 2059, "鱼": 2060, "身体": 2061, "怪怪": 2062, "斜躺": 2063, "水中": 2064, "偶尔": 2065, "鱼鳍": 2066, "晃动": 2067, "敏感": 2068, "心口": 2069, "仿佛": 2070, "湿湿的": 2071, "水迹": 2072, "刹那间": 2073, "只能": 2074, "无助": 2075, "说不出来": 2076, "鼻子": 2077, "一酸": 2078, "吧嗒": 2079, "高年级": 2080, "与众不同": 2081, "在于": 2082, "一年四季": 2083, "校纪": 2084, "校规": 2085, "打架斗殴": 2086, "稳定性": 2087, "融入": 2088, "言行不一": 2089, "口是心非": 2090, "预见": 2091, "后果": 2092, "内驱": 2093, "目的": 2094, "不明": 2095, "不正": 2096, "意志薄弱": 2097, "糟糕": 2098, "加上": 2099, "性情": 2100, "古怪": 2101, "暴躁": 2102, "背地里": 2103, "冷面": 2104, "杀手": 2105, "犟头": 2106, "倔脑": 2107, "不屑一顾": 2108, "小金": 2109, "最为": 2110, "显著": 2111, "另类": 2112, "特征": 2113, "算是": 2114, "福分": 2115, "列为": 2116, "缺点": 2117, "便": 2118, "暴露": 2119, "基本": 2120, "话茬": 2121, "唯独": 2122, "韩": 2123, "大个子": 2124, "不是故意": 2125, "队伍": 2126, "走动": 2127, "扯": 2128, "前排": 2129, "矮小": 2130, "买": 2131, "教官": 2132, "练习": 2133, "队形": 2134, "竟然": 2135, "前面": 2136, "当场": 2137, "转过身": 2138, "韩某": 2139, "直接": 2140, "流血": 2141, "男孩": 2142, "送到": 2143, "校医": 2144, "室": 2145, "通知": 2146, "双方": 2147, "有点像": 2148, "周杰伦": 2149, "不错": 2150, "放在眼里": 2151, "直到": 2152, "八年级": 2153, "发呆": 2154, "富于": 2155, "时常": 2156, "口角": 2157, "乃至": 2158, "偏执": 2159, "轻微": 2160, "暴力": 2161, "以及": 2162, "被害": 2163, "妄想症": 2164, "大小": 2165, "摩擦": 2166, "频繁": 2167, "小鹏": 2168, "非常简单": 2169, "小鹏发": 2170, "不一会儿": 2171, "报告": 2172, "沈某": 2173, "包某": 2174, "戚某": 2175, "徐某": 2176, "朱某": 2177, "放到": 2178, "可谓": 2179, "说不出": 2180, "作文课": 2181, "航模": 2182, "花盆": 2183, "当球": 2184, "几只": 2185, "一大堆": 2186, "拿到": 2187, "阳光": 2188, "暴晒": 2189, "窗台上": 2190, "口袋": 2191, "可恶": 2192, "但小轩": 2193, "易怒": 2194, "攻击": 2195, "善于": 2196, "交往": 2197, "陈": 2198, "好奇": 2199, "交涉": 2200, "成功": 2201, "硬来": 2202, "抢": 2203, "无理": 2204, "破口大骂": 2205, "捶": 2206, "两拳": 2207, "星期五": 2208, "早上": 2209, "溅湿": 2210, "衣襟": 2211, "尽管": 2212, "连忙": 2213, "怒不可遏": 2214, "书桌": 2215, "全": 2216, "掀到": 2217, "小川": 2218, "之内": 2219, "抓": 2220, "三个": 2221, "全都": 2222, "面部": 2223, "周围": 2224, "周五": 2225, "眼镜": 2226, "儿": 2227, "便池": 2228, "踩水": 2229, "冲走": 2230, "姥姥": 2231, "翻": 2232, "垃圾筒": 2233, "列举": 2234, "抓人": 2235, "之外": 2236, "例如": 2237, "鼻尖": 2238, "铅笔尖": 2239, "扎人": 2240, "盼望着": 2241, "饭盒": 2242, "作为": 2243, "让萍萍": 2244, "承担": 2245, "公平": 2246, "撕掉": 2247, "分作": 2248, "两半": 2249, "撕烂": 2250, "作对": 2251, "嘛": 2252, "约定": 2253, "规则": 2254, "触犯": 2255, "公开挑衅": 2256, "后排": 2257, "喝空": 2258, "饮料瓶": 2259, "头上": 2260, "当即": 2261, "瓶子": 2262, "回敬": 2263, "那名": 2264, "谩骂": 2265, "钢笔": 2266, "连刺": 2267, "臂膀": 2268, "5": 2269, "鲜血": 2270, "直流": 2271, "严厉批评": 2272, "满不在乎": 2273, "长调": 2274, "生怕": 2275, "听不出": 2276, "总爱": 2277, "保护意识": 2278, "强": 2279, "占": 2280, "上风": 2281, "肯": 2282, "罢休": 2283, "赵磊": 2284, "比班内": 2285, "大一到": 2286, "两岁": 2287, "留过级": 2288, "义气": 2289, "品性": 2290, "散漫": 2291, "贪玩": 2292, "社会": 2293, "无业": 2294, "青年": 2295, "最终": 2296, "酿成": 2297, "脏": 2298, "一片": 2299, "胆小": 2300, "言听计从": 2301, "操行": 2302, "处理": 2303, "讲到": 2304, "扣": 2305, "期望": 2306, "自觉": 2307, "做好": 2308, "放屁": 2309, "寻": 2310, "声望去": 2311, "出自": 2312, "陈明": 2313, "之口": 2314, "随着": 2315, "推移": 2316, "部分": 2317, "班干": 2318, "XXX": 2319, "抄": 2320, "陆续": 2321, "粗暴": 2322, "参加": 2323, "游戏": 2324, "推倒": 2325, "搅得": 2326, "安宁": 2327, "懂": 2328, "课外": 2329, "知识": 2330, "因而": 2331, "嘲笑": 2332, "真正": 2333, "允许": 2334, "满意": 2335, "值班": 2336, "来得及": 2337, "晚上": 2338, "母亲": 2339, "大吵": 2340, "差一点": 2341, "还动": 2342, "引发": 2343, "指责": 2344, ";": 2345, "顶": 2346, "十句": 2347, "后门": 2348, "两步": 2349, "跟上来": 2350, "意思": 2351, "用力": 2352, "地要": 2353, "甩开": 2354, "硬": 2355, "压下去": 2356, "火": 2357, "陡然": 2358, "串": 2359, "敢": 2360, "如此": 2361, "正面": 2362, "教师": 2363, "主动": 2364, "劝说": 2365, "多名": 2366, "为此": 2367, "头痛": 2368, "课余时间": 2369, "闹矛盾": 2370, "捏": 2371, "耳朵": 2372, "薅": 2373, "小辫子": 2374, "携带": 2375, "凳": 2376, "墨水瓶": 2377, "洗衣粉": 2378, "上滴": 2379, "美其名曰": 2380, "太阳镜": 2381, "追着": 2382, "喷射": 2383, "彝语": 2384, "乱说": 2385, "耍赖": 2386, "有时候": 2387, "好笑": 2388, "好气": 2389, "中有": 2390, "或值": 2391, " ": 2392, "周": 2393, "惹事生非": 2394, "信号": 2395, "放肆": 2396, "大笑": 2397, "如果": 2398, "振振有词": 2399, "地为": 2400, "狡辫": 2401, "排练": 2402, "稍长": 2403, "点": 2404, "耐不住": 2405, "认真": 2406, "拖": 2407, "出列": 2408, "咬了一口": 2409, "深深": 2410, "牙印": 2411, "管教": 2412, "反应": 2413, "A": 2414, "响亮": 2415, "幸灾乐祸": 2416, "愣住": 2417, "一个班": 2418, "带班": 2419, "此刻": 2420, "普遍现象": 2421, "背着": 2422, "接送": 2423, "上下学": 2424, "超多": 2425, "零花钱": 2426, "玩具": 2427, "稍": 2428, "没顺": 2429, "意": 2430, "现象": 2431, "由于": 2432, "家庭环境": 2433, "优越": 2434, "吸烟": 2435, "喝酒": 2436, "无拘无束": 2437, "后勤": 2438, "科长": 2439, "直至": 2440, "小李": 2441, "相处": 2442, "因": 2443, "琐事": 2444, "相同": 2445, "共识": 2446, "易": 2447, "分散": 2448, "烫手": 2449, "山芋": 2450, "双差生": 2451, "小磊": 2452, "": 2453, "动脑": 2454, "侵犯": 2455, "注意": 2456, "背上": 2457, "灰洒": 2458, "尤为": 2459, "教小明": 2460, "": 2461, "弱智": 2462, "": 2463, "时时": 2464, "欺侮": 2465, "约束": 2466, "能力差": 2467, "头脑": 2468, "观念": 2469, "迟到": 2470, "早退": 2471, "所犯": 2472, "张": 2473, "佳音": 2474, "先天性": 2475, "高一": 2476, "违纪": 2477, "黄卡": 2478, "谆谆教导": 2479, "苦苦哀求": 2480, "专心": 2481, "提不起": 2482, "名叫": 2483, "周越": 2484, "珊": 2485, "认真听讲": 2486, "敷衍了事": 2487, "总有": 2488, "初一": 2489, "做作业": 2490, "各门": 2491, "功课": 2492, "单元测试": 2493, "不及格": 2494, "冲动": 2495, "群众": 2496, "荣誉感": 2497, "对待": 2498, "友善": 2499, "欺压": 2500, "中学": 2501, "之前": 2502, "发生冲突": 2503, "持刀": 2504, "带人": 2505, "一所": 2506, "幸好": 2507, "警察": 2508, "及时": 2509, "赶到": 2510, "外校": 2511, "自身": 2512, "不足之处": 2513, "加以": 2514, "改正": 2515, "一个月": 2516, "初三": 2517, "年级": 2518, "借钱": 2519, "不思悔改": 2520, "欲": 2521, "现场": 2522, "束手无策": 2523, "上学时": 2524, "-": 2525, "才气": 2526, "潜力": 2527, "用心": 2528, "废话连篇": 2529, "老师上课": 2530, "一齐": 2531, "玩儿": 2532, "小动作": 2533, "劝告": 2534, "长": 2535, "吵闹": 2536, "本人": 2537, "言善辨": 2538, "懂得": 2539, "道理": 2540, "家庭教育": 2541, "环境影响": 2542, "方面": 2543, "一向": 2544, "产生": 2545, "遵守": 2546, "喊": 2547, "无关": 2548, "狡辨": 2549, "兴趣十足": 2550, "讨论": 2551, "事隔": 2552, "进行批评": 2553, "一贯": 2554, "不爱": 2555, "相伴": 2556, "任课教师": 2557, "抬": 2558, "抬杠": 2559, "挖苦": 2560, "讽刺": 2561, "还常": 2562, "生事": 2563, "刚进": 2564, "文公": 2565, "违反": 2566, "如": 2567, "几经周折": 2568, "重新": 2569, "高二": 2570, "4": 2571, "转来": 2572, "吴非": 2573, "极强": 2574, "犟": 2575, "生活": 2576, "自制力": 2577, "扛": 2578, "地因": 2579, "拌嘴": 2580, "张扬": 2581}